fpga/src/spi.sv
// spi.sv
// Mayu Tatsumi; mtatsumi@g.hmc.edu
// Quinn Miyamoto; qmiyamoto@g.hmc.edu
// 2025-11-30

// Toggle-handshake CDC, 16-bit PCM -> MCU via SPI (no CS, no SDI)

module spi (
    input  logic        clk,           // 1.536 MHz (audio domain)
    input  logic        clk_6mhz,      // 6 MHz (SPI clock source)
    input  logic        reset_n,
    
    input  logic        audio_valid,   // clk domain
    input  logic [15:0] pcm_out,       // clk domain

    output logic        sck,           // to MCU (SPI SCK)
    output logic        sdo,           // to MCU (MOSI)
	output logic        cs
);

	// note to self: debugging with busy and sck_enable made the sck/sdo output hella... idk why

    /*

    1. clk (1.536 MHz) domain
        * latch pcm_out into local buffer
        * toggle req_toggle to signal new data ready

    2. cross clock domains (clk -> clk_6mhz)
        * synchronize req_toggle -> req_sync1
        * assume pcm_latched is stable when req_toggle crosses (std. handshake scheme)
    
    3. clk_6mhz (6 MHz) domain
        * detect changes in req_sync1 (new request)
        * SPI transmitter 2-state FSM (based on 'busy' signal)
            - idle when not busy
            - on new request: load pcm_latched into shift register & set busy
            - when busy: shift out 16 bits MSB first on sdo & generate sck (3 MHz)
            - busy also works as the inverse chip select

    */

    // 1. CLK DOMAIN LOGIC
    // store sample and toggle request

    logic audio_valid_d;            // used for edge detection
    logic req_toggle;               // toggled when new sample is ready, signals to SPI domain
    logic [15:0] pcm_latched;       // local buffer
	
    logic audio_valid_rise;         // REGISTERED edge detection signal

    // Edge detection for audio_valid (REGISTERED VERSION)
    // This avoids X propagation issues in simulation
    always_ff @(posedge clk or negedge reset_n) begin
        if (~reset_n) begin
            audio_valid_d    <= 1'b0;
            audio_valid_rise <= 1'b0;
        end else begin
            audio_valid_d    <= audio_valid;
            audio_valid_rise <= audio_valid & ~audio_valid_d;  // Register the edge detect
        end
    end

	logic [15:0] fake_data;
	assign fake_data = 16'b1100110011001100;

    // main handshake:
    // on rising edge of audio_valid:
    //      store PCM sample in pcm_latched (temporarily!)
    //      toggle req_toggle to signal to SPI domain that new data is ready
    
    // later: SPI domain will detect the toggle and transmit the latched data
    always_ff @(posedge clk or negedge reset_n) begin
        if (~reset_n) begin
            req_toggle  <= 1'b0;
            pcm_latched <= 16'h0000;
        end else begin
            if (audio_valid_rise) begin
                pcm_latched <=  pcm_out;			// DEBUG: fake_data;
                req_toggle  <= ~req_toggle;
            end
        end
    end


    // 2. CLOCK DOMAIN CROSSING / SYNCHRONIZERS
    // clk -> clk_6mhz
    
    // req_toggle -> req_sync1 (std. 2-flop synchronizer)
    logic req_sync0, req_sync1;
    always_ff @(posedge clk_6mhz or negedge reset_n) begin
        if (~reset_n) begin
            req_sync0 <= 1'b0;
            req_sync1 <= 1'b0;
        end else begin
            req_sync0 <= req_toggle;
            req_sync1 <= req_sync0;
        end
    end


    // 3. SPI TRANSMITTER LOGIC, ALL 6 MHZ DOMAIN
    // single-bit fsm (busy or not) to shift out 16 bits (msb first) thru sdo & generate sck
    // SPI mode 0: cpol=0, cpha=0 AKA idle low, data latched on rising edge of sck
    
    logic req_toggle_local;     // detect changes in req_toggle by storing a local copy
    logic new_request_6mhz;     // high for one clk_6mhz cycle when new request detected

    always_ff @(posedge clk_6mhz or negedge reset_n) begin
        if (~reset_n) begin
            req_toggle_local <= 1'b0;
        end else begin
            req_toggle_local <= req_sync1;
        end
    end
    assign new_request_6mhz = (req_sync1 != req_toggle_local);


    logic        busy;          // high when transmitting, controls main 2-state FSM & sck generation

    logic [15:0] shift_reg;     // holds data being shifted out
    logic [4:0]  bit_count;     // # remaining bits, 16 -> 0
    logic        sck_enable;    // toggles to generate sck edges
    
    // sck generation: toggle when busy (6 MHz / 2 = 3 MHz SCK)
    always_ff @(posedge clk_6mhz or negedge reset_n) begin
        if (~reset_n) begin
            busy <= 1'b0;

            shift_reg <= 16'h0000;
            bit_count <= 5'd0;

            sck_enable <= 1'b0;
            sdo <= 1'b0;
            sck <= 1'b0;
        end else begin
            if (~busy) begin
                // not busy: idle low (mode 0)
                sck <= 1'b0;                    
                if (new_request_6mhz) begin
                    // load new data into shift register & start transmission
                    shift_reg <= pcm_latched;   // pcm_latched is stable due to handshake
                    bit_count <= 5'd16;         // 16 bits to send
                    busy <= 1'b1;               // enter busy state
                    sck_enable <= 1'b0;         // prep to toggle

                    sdo <= pcm_latched[15];     // output MSB first
                end
            end else begin
                // busy state: transmitting data & toggle sck_enable every cycle
                sck_enable <= ~sck_enable;          // enable sck toggling

                if (~sck_enable) begin       // POSEDGE of SCK: MCU samples here
                    sck <= 1'b1;
                end else begin                      // NEGEDGE of SCK: shift data here
                   sck <= 1'b0; 
				   bit_count <= bit_count - 1'b1;
				   
				   if (bit_count == 5'd1) begin 	// finished transmitting last bit
					   busy <= 1'b0;
					   sdo <= 1'b0;
					end else begin
                        shift_reg <= {shift_reg[14:0], 1'b0};       // shift left
                        sdo <= shift_reg[14];                       // next bit to output
                    end
                end
            end
        end
    end
	
	assign cs = ~busy;
    
endmodule

spi_tb.sv
`timescale 1ns / 1ps

module spi_tb;

    // Clock and reset
    logic        clk;           // 1.536 MHz (period = 651.04 ns)
    logic        clk_6mhz;      // 6 MHz (period = 166.67 ns)
    logic        reset_n;
    
    // Audio interface
    logic        audio_valid;
    logic [15:0] pcm_out;
    
    // SPI interface
    logic        sck;
    logic        sdo;
    
    // DUT instantiation
    spi dut (
        .clk(clk),
        .clk_6mhz(clk_6mhz),
        .reset_n(reset_n),
        .audio_valid(audio_valid),
        .pcm_out(pcm_out),
        .sck(sck),
        .sdo(sdo)
    );
    
    // Clock generation
    // 1.536 MHz clock (period = 651.04 ns)
    initial begin
        clk = 0;
        forever #325.52 clk = ~clk;  // Half period = 325.52 ns
    end
    
    // 6 MHz clock (period = 166.67 ns)
    initial begin
        clk_6mhz = 0;
        forever #83.33 clk_6mhz = ~clk_6mhz;  // Half period = 83.33 ns
    end
    
    // Task to send audio sample
    task send_audio_sample(input [15:0] data);
        begin
            pcm_out = data;
            @(posedge clk);
            audio_valid = 1'b1;
            @(posedge clk);
            audio_valid = 1'b0;
            $display("[%0t] Sent audio sample: 0x%04h", $time, data);
        end
    endtask
    
    // Task to monitor SPI transmission
    // Note: Variables are now LOCAL (automatic) to avoid race conditions
    task monitor_spi_transmission();
        logic [15:0] received_data;  // LOCAL to this task call
        int bit_index;               // LOCAL to this task call
        begin
            received_data = 16'h0000;
            bit_index = 15;
            
            $display("[%0t] Waiting for SPI transmission to start...", $time);
            
            // Wait for SCK to go high (start of first bit in Mode 0)
            fork
                begin
                    @(posedge sck);
                    $display("[%0t] SPI transmission started", $time);
                end
                begin
                    #50000;  // 50us timeout for transmission start
                    $display("ERROR [%0t]: Timeout waiting for SPI transmission start", $time);
                    $finish;
                end
            join_any
            disable fork;
            
            // Capture 16 bits on rising edges
            for (int i = 0; i < 16; i++) begin
                received_data[bit_index] = sdo;
                $display("[%0t] Bit %0d captured: SDO=%b", $time, 15-bit_index, sdo);
                bit_index--;
                if (i < 15) @(posedge sck);  // Wait for next bit
            end
            
            $display("[%0t] === SPI transmission complete. Received: 0x%04h (binary: %016b) ===", 
                     $time, received_data, received_data);
        end
    endtask
    
    // Main test sequence
    initial begin
        // Initialize - CRITICAL: Set all inputs to known values
        reset_n = 0;
        audio_valid = 0;
        pcm_out = 16'h0000;
        
        // VCD dump for waveform viewing
        $dumpfile("spi_tb.vcd");
        $dumpvars(0, spi_tb);
        
        // Reset
        $display("========================================");
        $display("Starting SPI Testbench");
        $display("========================================");
        
        // Hold reset for several clock cycles
        repeat(10) @(posedge clk);
        reset_n = 1;
        $display("[%0t] Reset released", $time);
        
        // Wait for synchronizers to settle (important for CDC)
        repeat(20) @(posedge clk);
        $display("[%0t] Initialization complete, ready for tests", $time);
        
        // Test 1: Send single sample
        $display("\n--- Test 1: Single Sample Transmission ---");
        fork
            send_audio_sample(16'hA5A5);
            monitor_spi_transmission();
        join
        
        // Wait for transmission to complete
        repeat(50) @(posedge clk_6mhz);
        
        // Test 2: Send another sample with different pattern
        $display("\n--- Test 2: Second Sample Transmission ---");
        fork
            send_audio_sample(16'h5A5A);
            monitor_spi_transmission();
        join
        
        repeat(50) @(posedge clk_6mhz);
        
        // Test 3: Send all 1s
        $display("\n--- Test 3: All 1s Pattern ---");
        fork
            send_audio_sample(16'hFFFF);
            monitor_spi_transmission();
        join
        
        repeat(50) @(posedge clk_6mhz);
        
        // Test 4: Send all 0s
        $display("\n--- Test 4: All 0s Pattern ---");
        fork
            send_audio_sample(16'h0000);
            monitor_spi_transmission();
        join
        
        repeat(50) @(posedge clk_6mhz);
        
        // Test 5: Back-to-back samples at realistic 16 kHz rate (stress test)
        $display("\n--- Test 5: Realistic 16 kHz Sample Rate ---");
        $display("Expected: 62.5 us between samples (16 kHz)");
        fork
            begin
                send_audio_sample(16'h1234);
                #62500;  // 62.5 us delay (realistic 16 kHz rate)
                send_audio_sample(16'h5678);
                #62500;  // Another sample
                send_audio_sample(16'h9ABC);
            end
            begin
                monitor_spi_transmission();
                monitor_spi_transmission();
                monitor_spi_transmission();
            end
        join
        
        repeat(100) @(posedge clk_6mhz);
        
        $display("\n========================================");
        $display("Testbench Complete");
        $display("========================================");
        $finish;
    end
    
    // Timeout watchdog
    initial begin
        #1000000;  // 1ms timeout
        $display("ERROR: Testbench timeout!");
        $finish;
    end
    
    // Monitor for SCK and SDO changes (only during active transmission)
    always @(posedge dut.busy) begin
        $display("[%0t] >>> SPI BUSY asserted, transmission starting", $time);
    end
    
    always @(negedge dut.busy) begin
        $display("[%0t] <<< SPI BUSY deasserted, transmission complete", $time);
    end
    
    // Check SPI Mode 0 compliance
    initial begin
        @(posedge reset_n);
        forever begin
            @(negedge reset_n or posedge sck);
            if (reset_n) begin
                // In Mode 0, SCK should be low when idle
                @(negedge dut.busy);
                #100;  // Wait a bit after transmission
                if (sck !== 1'b0) begin
                    $display("ERROR [%0t]: SCK not idle low (Mode 0 violation)!", $time);
                end
            end
        end
    end
    
    // Debug monitor for internal signals
    always @(posedge clk) begin
        if (reset_n && audio_valid) begin
            $display("[%0t DEBUG] audio_valid pulse detected in 1.536MHz domain", $time);
        end
    end
    
    always @(posedge clk_6mhz) begin
        if (reset_n && dut.new_request_6mhz) begin
            $display("[%0t DEBUG] new_request detected in 6MHz domain", $time);
        end
    end

endmodule

fpga/work/spi_tb.vcd
$date
	Sat Dec  6 16:30:31 2025
$end
$version
	Questa Lattice OEM Edition 2024.2
$end
$timescale
	1ps
$end

$scope module spi_tb $end
$var reg 1 ! clk $end
$var reg 1 " clk_6mhz $end
$var reg 1 # reset_n $end
$var reg 1 $ audio_valid $end
$var reg 16 % pcm_out [15:0] $end
$var reg 1 & sck $end
$var reg 1 ' sdo $end

$scope task send_audio_sample $end
$var reg 16 ( data [15:0] $end
$upscope $end

$scope task monitor_spi_transmission $end
$var reg 16 ) received_data [15:0] $end
$var integer 32 * bit_index $end
$upscope $end

$scope module dut $end
$var wire 1 + clk $end
$var wire 1 , clk_6mhz $end
$var wire 1 - reset_n $end
$var wire 1 . audio_valid $end
$var wire 1 / pcm_out [15] $end
$var wire 1 0 pcm_out [14] $end
$var wire 1 1 pcm_out [13] $end
$var wire 1 2 pcm_out [12] $end
$var wire 1 3 pcm_out [11] $end
$var wire 1 4 pcm_out [10] $end
$var wire 1 5 pcm_out [9] $end
$var wire 1 6 pcm_out [8] $end
$var wire 1 7 pcm_out [7] $end
$var wire 1 8 pcm_out [6] $end
$var wire 1 9 pcm_out [5] $end
$var wire 1 : pcm_out [4] $end
$var wire 1 ; pcm_out [3] $end
$var wire 1 < pcm_out [2] $end
$var wire 1 = pcm_out [1] $end
$var wire 1 > pcm_out [0] $end
$var reg 1 ? sck $end
$var reg 1 @ sdo $end
$var reg 1 A cs $end
$var reg 1 B audio_valid_d $end
$var reg 1 C req_toggle $end
$var reg 16 D pcm_latched [15:0] $end
$var reg 1 E audio_valid_rise $end
$var reg 16 F fake_data [15:0] $end
$var reg 1 G req_sync0 $end
$var reg 1 H req_sync1 $end
$var reg 1 I req_toggle_local $end
$var reg 1 J new_request_6mhz $end
$var reg 1 K busy $end
$var reg 16 L shift_reg [15:0] $end
$var reg 5 M bit_count [4:0] $end
$var reg 1 N sck_enable $end
$upscope $end
$upscope $end
$enddefinitions $end
#0
$dumpvars
0!
0"
0#
0$
b0 %
0&
0'
0?
0@
1A
0B
0C
b0 D
0E
b1100110011001100 F
0G
0H
0I
0J
0K
b0 L
b0 M
0N
bx (
bx )
b0 *
0>
0=
0<
0;
0:
09
08
07
06
05
04
03
02
01
00
0/
0.
0-
0,
0+
$end
#83330
1"
1,
#166660
0"
0,
#249990
1"
1,
#325520
1!
1+
#333320
0"
0,
#416650
1"
1,
#499980
0"
0,
#583310
1"
1,
#651040
0!
0+
#666640
0"
0,
#749970
1"
1,
#833300
0"
0,
#916630
1"
1,
#976560
1!
1+
#999960
0"
0,
#1083290
1"
1,
#1166620
0"
0,
#1249950
1"
1,
#1302080
0!
0+
#1333280
0"
0,
#1416610
1"
1,
#1499940
0"
0,
#1583270
1"
1,
#1627600
1!
1+
#1666600
0"
0,
#1749930
1"
1,
#1833260
0"
0,
#1916590
1"
1,
#1953120
0!
0+
#1999920
0"
0,
#2083250
1"
1,
#2166580
0"
0,
#2249910
1"
1,
#2278640
1!
1+
#2333240
0"
0,
#2416570
1"
1,
#2499900
0"
0,
#2583230
1"
1,
#2604160
0!
0+
#2666560
0"
0,
#2749890
1"
1,
#2833220
0"
0,
#2916550
1"
1,
#2929680
1!
1+
#2999880
0"
0,
#3083210
1"
1,
#3166540
0"
0,
#3249870
1"
1,
#3255200
0!
0+
#3333200
0"
0,
#3416530
1"
1,
#3499860
0"
0,
#3580720
1!
1+
#3583190
1"
1,
#3666520
0"
0,
#3749850
1"
1,
#3833180
0"
0,
#3906240
0!
0+
#3916510
1"
1,
#3999840
0"
0,
#4083170
1"
1,
#4166500
0"
0,
#4231760
1!
1+
#4249830
1"
1,
#4333160
0"
0,
#4416490
1"
1,
#4499820
0"
0,
#4557280
0!
0+
#4583150
1"
1,
#4666480
0"
0,
#4749810
1"
1,
#4833140
0"
0,
#4882800
1!
1+
#4916470
1"
1,
#4999800
0"
0,
#5083130
1"
1,
#5166460
0"
0,
#5208320
0!
0+
#5249790
1"
1,
#5333120
0"
0,
#5416450
1"
1,
#5499780
0"
0,
#5533840
1!
1+
#5583110
1"
1,
#5666440
0"
0,
#5749770
1"
1,
#5833100
0"
0,
#5859360
0!
0+
#5916430
1"
1,
#5999760
0"
0,
#6083090
1"
1,
#6166420
0"
0,
#6184880
1!
1+
1#
1-
#6249750
1"
1,
#6333080
0"
0,
#6416410
1"
1,
#6499740
0"
0,
#6510400
0!
0+
#6583070
1"
1,
#6666400
0"
0,
#6749730
1"
1,
#6833060
0"
0,
#6835920
1!
1+
#6916390
1"
1,
#6999720
0"
0,
#7083050
1"
1,
#7161440
0!
0+
#7166380
0"
0,
#7249710
1"
1,
#7333040
0"
0,
#7416370
1"
1,
#7486960
1!
1+
#7499700
0"
0,
#7583030
1"
1,
#7666360
0"
0,
#7749690
1"
1,
#7812480
0!
0+
#7833020
0"
0,
#7916350
1"
1,
#7999680
0"
0,
#8083010
1"
1,
#8138000
1!
1+
#8166340
0"
0,
#8249670
1"
1,
#8333000
0"
0,
#8416330
1"
1,
#8463520
0!
0+
#8499660
0"
0,
#8582990
1"
1,
#8666320
0"
0,
#8749650
1"
1,
#8789040
1!
1+
#8832980
0"
0,
#8916310
1"
1,
#8999640
0"
0,
#9082970
1"
1,
#9114560
0!
0+
#9166300
0"
0,
#9249630
1"
1,
#9332960
0"
0,
#9416290
1"
1,
#9440080
1!
1+
#9499620
0"
0,
#9582950
1"
1,
#9666280
0"
0,
#9749610
1"
1,
#9765600
0!
0+
#9832940
0"
0,
#9916270
1"
1,
#9999600
0"
0,
#10082930
1"
1,
#10091120
1!
1+
#10166260
0"
0,
#10249590
1"
1,
#10332920
0"
0,
#10416250
1"
1,
#10416640
0!
0+
#10499580
0"
0,
#10582910
1"
1,
#10666240
0"
0,
#10742160
1!
1+
#10749570
1"
1,
#10832900
0"
0,
#10916230
1"
1,
#10999560
0"
0,
#11067680
0!
0+
#11082890
1"
1,
#11166220
0"
0,
#11249550
1"
1,
#11332880
0"
0,
#11393200
1!
1+
#11416210
1"
1,
#11499540
0"
0,
#11582870
1"
1,
#11666200
0"
0,
#11718720
0!
0+
#11749530
1"
1,
#11832860
0"
0,
#11916190
1"
1,
#11999520
0"
0,
#12044240
1!
1+
#12082850
1"
1,
#12166180
0"
0,
#12249510
1"
1,
#12332840
0"
0,
#12369760
0!
0+
#12416170
1"
1,
#12499500
0"
0,
#12582830
1"
1,
#12666160
0"
0,
#12695280
1!
1+
#12749490
1"
1,
#12832820
0"
0,
#12916150
1"
1,
#12999480
0"
0,
#13020800
0!
0+
#13082810
1"
1,
#13166140
0"
0,
#13249470
1"
1,
#13332800
0"
0,
#13346320
1!
1+
#13416130
1"
1,
#13499460
0"
0,
#13582790
1"
1,
#13666120
0"
0,
#13671840
0!
0+
#13749450
1"
1,
#13832780
0"
0,
#13916110
1"
1,
#13997360
1!
1+
#13999440
0"
0,
#14082770
1"
1,
#14166100
0"
0,
#14249430
1"
1,
#14322880
0!
0+
#14332760
0"
0,
#14416090
1"
1,
#14499420
0"
0,
#14582750
1"
1,
#14648400
1!
1+
#14666080
0"
0,
#14749410
1"
1,
#14832740
0"
0,
#14916070
1"
1,
#14973920
0!
0+
#14999400
0"
0,
#15082730
1"
1,
#15166060
0"
0,
#15249390
1"
1,
#15299440
1!
1+
#15332720
0"
0,
#15416050
1"
1,
#15499380
0"
0,
#15582710
1"
1,
#15624960
0!
0+
#15666040
0"
0,
#15749370
1"
1,
#15832700
0"
0,
#15916030
1"
1,
#15950480
1!
1+
#15999360
0"
0,
#16082690
1"
1,
#16166020
0"
0,
#16249350
1"
1,
#16276000
0!
0+
#16332680
0"
0,
#16416010
1"
1,
#16499340
0"
0,
#16582670
1"
1,
#16601520
1!
1+
#16666000
0"
0,
#16749330
1"
1,
#16832660
0"
0,
#16915990
1"
1,
#16927040
0!
0+
#16999320
0"
0,
#17082650
1"
1,
#17165980
0"
0,
#17249310
1"
1,
#17252560
1!
1+
#17332640
0"
0,
#17415970
1"
1,
#17499300
0"
0,
#17578080
0!
0+
#17582630
1"
1,
#17665960
0"
0,
#17749290
1"
1,
#17832620
0"
0,
#17903600
1!
1+
#17915950
1"
1,
#17999280
0"
0,
#18082610
1"
1,
#18165940
0"
0,
#18229120
0!
0+
#18249270
1"
1,
#18332600
0"
0,
#18415930
1"
1,
#18499260
0"
0,
#18554640
1!
1+
#18582590
1"
1,
#18665920
0"
0,
#18749250
1"
1,
#18832580
0"
0,
#18880160
0!
0+
#18915910
1"
1,
#18999240
0"
0,
#19082570
1"
1,
#19165900
0"
0,
#19205680
1!
1+
b1010010110100101 (
b1010010110100101 %
b0 )
b1111 *
1>
1<
19
17
16
14
11
1/
#19249230
1"
1,
#19332560
0"
0,
#19415890
1"
1,
#19499220
0"
0,
#19531200
0!
0+
#19582550
1"
1,
#19665880
0"
0,
#19749210
1"
1,
#19832540
0"
0,
#19856720
1!
1+
1$
1.
#19915870
1"
1,
#19999200
0"
0,
#20082530
1"
1,
#20165860
0"
0,
#20182240
0!
0+
#20249190
1"
1,
#20332520
0"
0,
#20415850
1"
1,
#20499180
0"
0,
#20507760
1!
1+
0$
0.
1B
1E
#20582510
1"
1,
#20665840
0"
0,
#20749170
1"
1,
#20832500
0"
0,
#20833280
0!
0+
#20915830
1"
1,
#20999160
0"
0,
#21082490
1"
1,
#21158800
1!
1+
b1010010110100101 D
1C
0B
0E
#21165820
0"
0,
#21249150
1"
1,
1G
#21332480
0"
0,
#21415810
1"
1,
1H
1J
#21484320
0!
0+
#21499140
0"
0,
#21582470
1"
1,
b1010010110100101 L
b10000 M
1K
1@
1I
0J
1'
0A
#21665800
0"
0,
#21749130
1"
1,
1N
1?
1&
b1000000000000000 )
b1110 *
#21809840
1!
1+
#21832460
0"
0,
#21915790
1"
1,
0N
0?
b1111 M
b100101101001010 L
0@
0'
0&
#21999120
0"
0,
#22082450
1"
1,
1N
1?
1&
b1101 *
#22135360
0!
0+
#22165780
0"
0,
#22249110
1"
1,
0N
0?
b1110 M
b1001011010010100 L
1@
1'
0&
#22332440
0"
0,
#22415770
1"
1,
1N
1?
1&
b1010000000000000 )
b1100 *
#22460880
1!
1+
#22499100
0"
0,
#22582430
1"
1,
0N
0?
b1101 M
b10110100101000 L
0@
0'
0&
#22665760
0"
0,
#22749090
1"
1,
1N
1?
1&
b1011 *
#22786400
0!
0+
#22832420
0"
0,
#22915750
1"
1,
0N
0?
b1100 M
b101101001010000 L
0&
#22999080
0"
0,
#23082410
1"
1,
1N
1?
1&
b1010 *
#23111920
1!
1+
#23165740
0"
0,
#23249070
1"
1,
0N
0?
b1011 M
b1011010010100000 L
1@
1'
0&
#23332400
0"
0,
#23415730
1"
1,
1N
1?
1&
b1010010000000000 )
b1001 *
#23437440
0!
0+
#23499060
0"
0,
#23582390
1"
1,
0N
0?
b1010 M
b110100101000000 L
0@
0'
0&
#23665720
0"
0,
#23749050
1"
1,
1N
1?
1&
b1000 *
#23762960
1!
1+
#23832380
0"
0,
#23915710
1"
1,
0N
0?
b1001 M
b1101001010000000 L
1@
1'
0&
#23999040
0"
0,
#24082370
1"
1,
1N
1?
1&
b1010010100000000 )
b111 *
#24088480
0!
0+
#24165700
0"
0,
#24249030
1"
1,
0N
0?
b1000 M
b1010010100000000 L
0&
#24332360
0"
0,
#24414000
1!
1+
#24415690
1"
1,
1N
1?
1&
b1010010110000000 )
b110 *
#24499020
0"
0,
#24582350
1"
1,
0N
0?
b111 M
b100101000000000 L
0@
0'
0&
#24665680
0"
0,
#24739520
0!
0+
#24749010
1"
1,
1N
1?
1&
b101 *
#24832340
0"
0,
#24915670
1"
1,
0N
0?
b110 M
b1001010000000000 L
1@
1'
0&
#24999000
0"
0,
#25065040
1!
1+
#25082330
1"
1,
1N
1?
1&
b1010010110100000 )
b100 *
#25165660
0"
0,
#25248990
1"
1,
0N
0?
b101 M
b10100000000000 L
0@
0'
0&
#25332320
0"
0,
#25390560
0!
0+
#25415650
1"
1,
1N
1?
1&
b11 *
#25498980
0"
0,
#25582310
1"
1,
0N
0?
b100 M
b101000000000000 L
0&
#25665640
0"
0,
#25716080
1!
1+
#25748970
1"
1,
1N
1?
1&
b10 *
#25832300
0"
0,
#25915630
1"
1,
0N
0?
b11 M
b1010000000000000 L
1@
1'
0&
#25998960
0"
0,
#26041600
0!
0+
#26082290
1"
1,
1N
1?
1&
b1010010110100100 )
b1 *
#26165620
0"
0,
#26248950
1"
1,
0N
0?
b10 M
b100000000000000 L
0@
0'
0&
#26332280
0"
0,
#26367120
1!
1+
#26415610
1"
1,
1N
1?
1&
b0 *
#26498940
0"
0,
#26582270
1"
1,
0N
0?
b1 M
b1000000000000000 L
1@
1'
0&
#26665600
0"
0,
#26692640
0!
0+
#26748930
1"
1,
1N
1?
1&
b1010010110100101 )
b11111111111111111111111111111111 *
#26832260
0"
0,
#26915590
1"
1,
0N
0?
b0 M
0K
0@
0'
1A
0&
